[
  {
    "name": "Бензин",
    "service": "Расход",
    "cost": "-1500.00",
    "workers": [
      "Слава",
      "Саша",
      "Жека"
    ],
    "receivers": [
      "Артём"
    ],
    "timestamp": "06.10.2025, 10:47:40",
    "isExpense": true,
    "isPaid": false,
    "issuedMoney": [],
    "editHistory": []
  },
  {
    "name": "Бензин",
    "service": "Расход",
    "cost": "-1000.00",
    "workers": [
      "Слава",
      "Жека"
    ],
    "receivers": [
      "Артём"
    ],
    "timestamp": "05.10.2025, 08:50:05",
    "isExpense": true,
    "isPaid": false,
    "issuedMoney": [],
    "editHistory": []
  },
  {
    "name": "Еда",
    "service": "Расход",
    "cost": "-480.00",
    "workers": [
      "Коля"
    ],
    "receivers": [
      "Артём"
    ],
    "timestamp": "05.10.2025, 08:49:33",
    "isExpense": true,
    "isPaid": false,
    "issuedMoney": [],
    "editHistory": []
  },
  {
    "name": "Бензин",
    "service": "Расход",
    "cost": "-1000.00",
    "workers": [
      "Слава",
      "Жека"
    ],
    "receivers": [
      "Артём"
    ],
    "timestamp": "04.10.2025, 08:44:37",
    "isExpense": true,
    "isPaid": false,
    "issuedMoney": [],
    "editHistory": []
  },
  {
    "name": "Бензин",
    "service": "Расход",
    "cost": "-500.00",
    "workers": [
      "Слава",
      "Жека"
    ],
    "receivers": [
      "Артём"
    ],
    "timestamp": "04.10.2025, 08:44:00",
    "isExpense": true,
    "isPaid": false,
    "issuedMoney": [],
    "editHistory": []
  },
  {
    "name": "Примыкания жекины",
    "service": "Расход",
    "cost": "-10000.00",
    "workers": [
      "Жека"
    ],
    "receivers": [
      "Артём"
    ],
    "timestamp": "02.10.2025, 14:44:29",
    "isExpense": true,
    "isPaid": false,
    "issuedMoney": [],
    "editHistory": []
  },
  {
    "name": "Бензин",
    "service": "Расход",
    "cost": "-1000.00",
    "workers": [
      "Слава",
      "Саша"
    ],
    "receivers": [
      "Артём"
    ],
    "timestamp": "02.10.2025, 10:56:13",
    "isExpense": true,
    "isPaid": false,
    "issuedMoney": [],
    "editHistory": []
  },
  {
    "name": "Займ",
    "service": "Расход",
    "cost": "-5000.00",
    "workers": [
      "Саша"
    ],
    "receivers": [
      "Артём"
    ],
    "timestamp": "01.10.2025, 20:37:58",
    "isExpense": true,
    "isPaid": false,
    "issuedMoney": [],
    "editHistory": []
  },
  {
    "name": "Бензин",
    "service": "Расход",
    "cost": "-250.00",
    "workers": [
      "Слава"
    ],
    "receivers": [
      "Артём"
    ],
    "timestamp": "01.10.2025, 20:36:37",
    "isExpense": true,
    "isPaid": false,
    "issuedMoney": [],
    "editHistory": []
  },
  {
    "name": "Бензин",
    "service": "Расход",
    "cost": "-250.00",
    "workers": [
      "Слава"
    ],
    "receivers": [
      "Артём"
    ],
    "timestamp": "30.09.2025, 21:18:03",
    "isExpense": true,
    "isPaid": false,
    "issuedMoney": [],
    "editHistory": []
  },
  {
    "name": "Бензин",
    "service": "Расход",
    "cost": "-500.00",
    "workers": [
      "Жека"
    ],
    "receivers": [
      "Артём"
    ],
    "timestamp": "30.09.2025, 21:17:50",
    "isExpense": true,
    "isPaid": false,
    "issuedMoney": [],
    "editHistory": []
  },
  {
    "name": "Галерея первая",
    "length": null,
    "width": null,
    "area": "1.00 м²",
    "service": "Монтаж наплавляемой кровли в 1 слой",
    "cost": "100.00",
    "workers": [
      {
        "name": "Артём",
        "ktu": 1,
        "cost": "16.67"
      },
      {
        "name": "Коля",
        "ktu": 1,
        "cost": "16.67"
      },
      {
        "name": "Слава",
        "ktu": 1,
        "cost": "16.67"
      },
      {
        "name": "Илья",
        "ktu": 1,
        "cost": "16.67"
      },
      {
        "name": "Саша",
        "ktu": 1,
        "cost": "16.67"
      },
      {
        "name": "Жека",
        "ktu": 1,
        "cost": "16.67"
      }
    ],
    "timestamp": "29.09.2025, 21:58:53",
    "isExpense": false,
    "isPaid": false,
    "useRostikMethod": false,
    "issuedMoney": [],
    "editHistory": []
  },
  {
    "name": "Парка боковая",
    "length": null,
    "width": null,
    "area": "1.00 м²",
    "service": "Монтаж наплавляемой кровли в 1 слой",
    "cost": "100.00",
    "workers": [
      {
        "name": "Артём",
        "ktu": 1,
        "cost": "16.67"
      },
      {
        "name": "Коля",
        "ktu": 1,
        "cost": "16.67"
      },
      {
        "name": "Слава",
        "ktu": 1,
        "cost": "16.67"
      },
      {
        "name": "Илья",
        "ktu": 1,
        "cost": "16.67"
      },
      {
        "name": "Саша",
        "ktu": 1,
        "cost": "16.67"
      },
      {
        "name": "Жека",
        "ktu": 1,
        "cost": "16.67"
      }
    ],
    "timestamp": "29.09.2025, 21:58:24",
    "isExpense": false,
    "isPaid": false,
    "useRostikMethod": false,
    "issuedMoney": [],
    "editHistory": []
  },
  {
    "name": "Теплушка",
    "length": null,
    "width": null,
    "area": "136.50 м²",
    "service": "Монтаж наплавляемой кровли в 1 слой",
    "cost": "13650.00",
    "workers": [
      {
        "name": "Артём",
        "ktu": 1,
        "cost": "2275.00"
      },
      {
        "name": "Коля",
        "ktu": 1,
        "cost": "2275.00"
      },
      {
        "name": "Слава",
        "ktu": 1,
        "cost": "2275.00"
      },
      {
        "name": "Илья",
        "ktu": 1,
        "cost": "2275.00"
      },
      {
        "name": "Саша",
        "ktu": 1,
        "cost": "2275.00"
      },
      {
        "name": "Жека",
        "ktu": 1,
        "cost": "2275.00"
      }
    ],
    "timestamp": "29.09.2025, 21:57:30",
    "isExpense": false,
    "isPaid": false,
    "useRostikMethod": false,
    "issuedMoney": [],
    "editHistory": []
  },
  {
    "name": "Займ",
    "service": "Расход",
    "cost": "-700.00",
    "workers": [
      "Саша"
    ],
    "receivers": [
      "Артём"
    ],
    "timestamp": "29.09.2025, 21:55:42",
    "isExpense": true,
    "isPaid": false,
    "issuedMoney": [],
    "editHistory": []
  },
  {
    "name": "Бензин",
    "service": "Расход",
    "cost": "-1500.00",
    "workers": [
      "Слава",
      "Саша",
      "Жека"
    ],
    "receivers": [
      "Артём"
    ],
    "timestamp": "29.09.2025, 21:55:24",
    "isExpense": true,
    "isPaid": false,
    "issuedMoney": [],
    "editHistory": []
  }
]